mcp_list/__init__.py
mcp_list/cli.py
mcp_list-0.1.0.dist-info/licenses/LICENSE
mcp_list-0.1.0.dist-info/METADATA
mcp_list-0.1.0.dist-info/WHEEL
mcp_list-0.1.0.dist-info/entry_points.txt
mcp_list-0.1.0.dist-info/top_level.txt
mcp_list-0.1.0.dist-info/RECORD
