Metadata-Version: 2.4
Name: mcp-list
Version: 0.1.0
Summary: List MCP servers and where they are configured
License: MIT License
Requires-Python: >=3.8
License-File: LICENSE
Requires-Dist: typer>=0.9.0
Requires-Dist: rich>=13.0.0
Dynamic: license-file
